.gitignore
.travis.yml
CHANGES.rst
COPYRIGHT.txt
LICENSE.txt
MANIFEST.in
README.txt
bootstrap.py
buildout.cfg
setup.py
src/zc/__init__.py
src/zc.monitor.egg-info/PKG-INFO
src/zc.monitor.egg-info/SOURCES.txt
src/zc.monitor.egg-info/dependency_links.txt
src/zc.monitor.egg-info/namespace_packages.txt
src/zc.monitor.egg-info/not-zip-safe
src/zc.monitor.egg-info/requires.txt
src/zc.monitor.egg-info/top_level.txt
src/zc/monitor/README.txt
src/zc/monitor/__init__.py
src/zc/monitor/interfaces.py
src/zc/monitor/tests.py
src/zc/monitor/unix-sockets.txt