Metadata-Version: 1.1
Name: zc.monitor
Version: 0.4.0.post1
Summary: A network-accessible command-line monitoring interface.
Home-page: https://github.com/zopefoundation/zc.monitor
Author: Jim Fulton
Author-email: jim@zope.com
License: ZPL 2.1
Keywords: zope3
Platform: UNKNOWN
Classifier: Development Status :: 5 - Production/Stable
Classifier: Intended Audience :: Developers
Classifier: License :: OSI Approved :: Zope Public License
Classifier: Programming Language :: Python
Classifier: Programming Language :: Python :: 2
Classifier: Programming Language :: Python :: 2.7
Classifier: Programming Language :: Python :: Implementation :: CPython
Classifier: Natural Language :: English
Classifier: Operating System :: OS Independent
Classifier: Topic :: Internet :: WWW/HTTP
